aaaawslogger/__init__.py
aaaawslogger/aws_logger.py
aaaawslogger/aws_logger_constants.py
aaaawslogger/awslogger.py
aaaawslogger/splunk.py
aws_logger/__init__.py
aws_logger/aws_logger.py
aws_logger_project/__init__.py
aws_logger_project/aws_logger.py
build/lib/aaaawslogger/__init__.py
build/lib/aaaawslogger/aws_logger.py
build/lib/aaaawslogger/aws_logger_constants.py
build/lib/aaaawslogger/awslogger.py
build/lib/aaaawslogger/splunk.py
build/lib/aws_logger/__init__.py
build/lib/aws_logger/aws_logger.py
build/lib/aws_logger_project/__init__.py
build/lib/aws_logger_project/aws_logger.py
build/lib/build/lib/aaaawslogger/__init__.py
build/lib/build/lib/aaaawslogger/aws_logger.py
build/lib/build/lib/aaaawslogger/aws_logger_constants.py
build/lib/build/lib/aaaawslogger/awslogger.py
build/lib/build/lib/aaaawslogger/splunk.py
build/lib/build/lib/aws_logger/__init__.py
build/lib/build/lib/aws_logger/aws_logger.py
build/lib/build/lib/aws_logger_project/__init__.py
build/lib/build/lib/aws_logger_project/aws_logger.py
build/lib/build/lib/build/lib/aaaawslogger/__init__.py
build/lib/build/lib/build/lib/aaaawslogger/aws_logger.py
build/lib/build/lib/build/lib/aaaawslogger/aws_logger_constants.py
build/lib/build/lib/build/lib/aaaawslogger/awslogger.py
build/lib/build/lib/build/lib/aaaawslogger/splunk.py
build/lib/build/lib/build/lib/aws_logger/__init__.py
build/lib/build/lib/build/lib/aws_logger/aws_logger.py
build/lib/build/lib/build/lib/aws_logger_project/__init__.py
build/lib/build/lib/build/lib/aws_logger_project/aws_logger.py
build/lib/build/lib/build/lib/build/lib/aaaawslogger/__init__.py
build/lib/build/lib/build/lib/build/lib/aaaawslogger/aws_logger.py
build/lib/build/lib/build/lib/build/lib/aaaawslogger/aws_logger_constants.py
build/lib/build/lib/build/lib/build/lib/aaaawslogger/awslogger.py
build/lib/build/lib/build/lib/build/lib/aaaawslogger/splunk.py
build/lib/build/lib/build/lib/build/lib/aws_logger/__init__.py
aaaawslogger-0.0.2.11.dist-info/METADATA
aaaawslogger-0.0.2.11.dist-info/WHEEL
aaaawslogger-0.0.2.11.dist-info/top_level.txt
aaaawslogger-0.0.2.11.dist-info/RECORD
