Metadata-Version: 2.1
Name: aaaawslogger
Version: 0.0.2.11
Summary: Logger
Author: ace
Author-email: kardaras.george@clublabs.com
Requires-Dist: boto3
